{
    "mediaId": "018f97ad-1a15-4b50-a927-e45e2256a546",
    "transcript": "for love? Plain and awkward! They'll take her for her connections and wealth. Are there no women living unmarried, and even the happier for it?\" So thought Prince Bolk6nski while dressing, and yet the question he was always putting off demanded an immediate answer. Prince Vasfli had brought his son with the evident inten- tion of proposing, and today or tomorrow he would probably ask for an answer. His birth and position in society were not bad. \"Well, I've nothing against it,\" the prince s",
    "createdDate": "2018-06-28T02:50:21.291Z",
    "speakers": [
        "Holly Franecki",
        "Mollie Rogahn"
    ],
    "categories": [
        "internal",
        "happy",
        "angry"
    ]
}