{
    "mediaId": "02efa588-38a3-455e-a286-126bb7918d99",
    "transcript": "hard brown face with its half-closed, dull, sleepy eyes. Prince Andrew gazed with anxious curiosity at that impassive face and wished he could tell what, if anything, this man was thinking and feeling at that moment. \"Is there anything at all be- hind that impassive face?\" Prince Andrew asked himself as he looked. Prince Bagrati6n bent his head in sign of agreement with what Prince Andrew told him, and said, \"Very good!\" in a tone that seemed to imply that everything that took place ",
    "createdDate": "2017-12-31T01:34:11.764Z",
    "speakers": [
        "Kobe Emard",
        "Casandra Jacobi"
    ],
    "categories": [
        "robocall",
        "confused",
        "internal",
        "complaint"
    ]
}