{
    "mediaId": "125ed0ba-7ca8-4315-b7f4-2df4a40fb2c6",
    "transcript": "longer listening to stories or telling them, but followed every movement of Rostov's hands and occasionally ran his eyes over the score against him. He had decided to play until that score reached forty-three thou- sand. He had fixed on that number because forty-three was the sum of his and S6nya's joint ages. Rost6v, leaning his head on both hands, sat at the table which was scrawled over with figures, wet with spilled wine, and littered with cards. One tormenting impression did not leave him",
    "createdDate": "2016-12-07T16:36:48.155Z",
    "speakers": [
        "Tiffany Hintz"
    ],
    "categories": []
}