{
    "mediaId": "22a571eb-e5a7-4c81-9be5-f7c9eff312a6",
    "transcript": "The most solemn mystery in the world continued its course. Evening passed, night came, and the feeling of suspense and softening of heart in the presence of the unfathomable did not lessen but in- creased. No one slept. \niIt was one of those March nights when win- ter seems to wish to resume its sway and scat- ters its last snows and storms with desperate fury. A relay of horses had been sent up the highroad to meet the German doctor from Moscow who was expected every moment, and men on",
    "createdDate": "2016-02-17T07:09:06.215Z",
    "speakers": [
        "Edwardo Jacobi"
    ],
    "categories": [
        "internal",
        "happy",
        "complaint"
    ]
}