{
    "mediaId": "26f05ce2-ef0b-4943-962f-2a0a55d78d7a",
    "transcript": " pretty?\" he asked with a wink. \n\"Why do you shout so? You'll frighten them ! \" said Boris. \"I did not expect you today,\" he added. \"I only sent you the note yesterday by Bolk6nski an adjutant of Kutuzov's, who's a friend of mine. I did not think he would get it \nto you so quickly Well, how are you? Been \nunder fire already?\" asked Boris. \nWithout answering, Rostov shook the sol- dier's Cross of St. George fastened to the cord- ing of his uniform and, indicating a bandaged arm, glanced at Berg w",
    "createdDate": "2016-07-06T23:35:28.886Z",
    "speakers": [
        "Kobe Emard",
        "Mollie Rogahn"
    ],
    "categories": [
        "angry"
    ]
}