{
    "mediaId": "2adc1cce-37d9-41ce-b211-0bbe03adae10",
    "transcript": "will not and cannot understand the Emperor Alexander's loftiness of soul. She tias refused to evacuate Malta. She wanted to find, and still seeks, some secret motive in our actions. What answer did Novosiltsev get? None. The English have not understood and cannot understand the self- abnegation of our Emperor who wants noth- ing for himself, but only desires the good of mankind. And what have they promised? Noth- ing! And what little they have promised they will not perform! Prussia has alw",
    "createdDate": "2015-12-23T13:14:16.572Z",
    "speakers": [
        "Brandy D'Amore"
    ],
    "categories": []
}