{
    "mediaId": "2ce419c0-a6b4-4df0-9590-cb4f3c33db6d",
    "transcript": "of the bedroom glanced at the princess and turned away. She did not venture to ask any questions, and shut the door again, now sitting down in her easy chair, now taking her prayer book, now kneeling before the icon stand. To her surprise and distress she found that her prayers did not calm her excitement. Suddenly her door opened softly and her old nurse, Pra- sk6vya Sdvishna, who hardly ever came to that \nroom as the old prince had forbidden it, ap- peared on the threshold with a shawl roun",
    "createdDate": "2018-11-25T03:13:25.128Z",
    "speakers": [
        "Kobe Emard"
    ],
    "categories": [
        "angry",
        "robocall",
        "internal"
    ]
}