{
    "mediaId": "3e6deda7-ce2b-4be8-82fe-1f2c9cfbea41",
    "transcript": "muttered to himself. \"How much is left in the puhse?\" he asked, turning to Rost6v. \n\"Seven new and three old imperials.\" \n\"Oh, it's wetched! Well, what are you stand- ing there for, you sca'cwow? Call the quahteh- masteh,\" he shouted to Lavrushka. \n\"Please, Denisov, let me lend you some: I have some, you know,\" said Rost6v, blushing. \n\"Don't like bowwowing from my own fel- lows, I don't/' growled Denisov. \n\"But if you won't accept money from me like a comrade, you will offend me. Really I have",
    "createdDate": "2017-01-18T12:53:08.095Z",
    "speakers": [
        "Kailyn Zulauf"
    ],
    "categories": [
        "happy"
    ]
}