{
    "mediaId": "47839219-d1ae-455f-b902-8c0d68090a0b",
    "transcript": " to laugh. \n\"It's a bad business, eh?\" \n\"What is bad, Father?\" \n\"The wife!\" said the old prince, briefly and significantly. \n\"I don't understand!\" said Prince Andrew. \n\"No, it can't be helped, lad,\" said the prince. \"They're all like that; one can't unmarry. Don't be afraid; I won't tell anyone, but you know it yourself.\" \nHe seized his son by the hand with small bony fingers, shook it, looked straight into his son's face with keen eyes which seemed to see through him, and again laughed his frig",
    "createdDate": "2018-10-27T09:00:39.194Z",
    "speakers": [
        "Holly Franecki"
    ],
    "categories": [
        "complaint",
        "support",
        "robocall",
        "happy"
    ]
}