{
    "mediaId": "47eb7598-169b-4592-9b88-1c3553610ffe",
    "transcript": " about, and still less what \"watching over his interests\" meant, but he decided that all these things had to be. From the passage they went into a large, dimly lit room adjoining the count's reception room. It was one of those sumptuous but cold apartments known to Pierre only from the front approach, but even in this room there now stood an empty bath, and water had been spilled on the carpet. They were met by a dea- con with a censer and by a servant who passed out on tiptoe without heeding th",
    "createdDate": "2017-11-07T10:42:00.130Z",
    "speakers": [
        "Godfrey Legros",
        "London Kautzer"
    ],
    "categories": [
        "support",
        "angry",
        "internal",
        "confused"
    ]
}