{
    "mediaId": "4ac5e9de-2e11-4664-8931-9cb72f1ee470",
    "transcript": " I thank you with my whole heart.\" To Rost6v every word sounded like a voice from heaven. How gladly would he have died at once for his Tsar! \n\"You have earned the St. George's standards and will be worthy of them.\" \n\"Oh, to die, to die for him!\" thought Rost6v. \nThe Tsar said something more which Ros- t6v did not hear, and the soldiers, straining their lungs, shouted \"Hurrah!\" \nRost6v too, bending over his saddle, shouted \"Hurrah!\" with all his might, feeling that he \nwould like to injure himse",
    "createdDate": "2019-04-11T16:17:43.744Z",
    "speakers": [
        "Mitchell White",
        "Korey Ziemann"
    ],
    "categories": [
        "support",
        "angry"
    ]
}