{
    "mediaId": "666980f1-e5ec-4def-a306-090b9bb949ad",
    "transcript": "and ran away. Anatole bowed to Prin- cess Mary with a gay smile, as if inviting her to join in a laugh at this strange incident, and then shrugging his shoulders went to the door that led to his own apartments. \nAn hour later, Ti'khon came to call Princess Mary to the old prince; he added that Prince Vasiii was also there. When Tikhon came to her Princess Mary was sitting on the sofa in her room, holding the weeping Mademoiselle Bourienne in her arms and gently stroking her hair. The princess",
    "createdDate": "2017-06-23T17:15:59.943Z",
    "speakers": [
        "Mitchell White",
        "Adalberto Doyle"
    ],
    "categories": [
        "happy"
    ]
}