{
    "mediaId": "7ae2d31b-40b6-4f38-a74c-66e8e27fcc16",
    "transcript": "immediately increased tenfold, and their life, which seemed to have been passed in darkness, was suddenly lit up by a new brightness, full of significance. \nPrincess Mary grew quite unconscious of her face and coiffure. The handsome open face of the man who might perhaps be her husband absorbed all her attention. He seemed to her kind, brave, determined, manly, and magnani- mous. She felt convinced of that. Thousands of dreams of a future family life continually rose in her imagination. Sh",
    "createdDate": "2017-02-07T08:59:35.029Z",
    "speakers": [
        "Nils Fritsch"
    ],
    "categories": [
        "angry",
        "confused",
        "support"
    ]
}