{
    "mediaId": "83d078ec-a7f5-4897-a332-c7ceb89f1712",
    "transcript": "in the skirmishing line . . . pass and watchword sh aft, Olmutz. What a nuisance that our squadron will be in reserve tomorrow/' he thought. \"I'll ask leave to go to the front, this may be my only chance of see- ing the Emperor. It won't be long now before I am off duty. I'll take another turn and when I get back I'll go to the general and ask him.\" He readjusted himself in the saddle and touched up his horse to ride once more round his hus- sars. It seemed to him that it was getting light- er",
    "createdDate": "2016-05-03T15:37:12.074Z",
    "speakers": [
        "Ricardo Streich",
        "Alaina Brown"
    ],
    "categories": []
}