{
    "mediaId": "864bf17d-b793-4daf-a096-c5991f89c207",
    "transcript": "he had no time to ask himself whether these people were sincere or not. He was always busy and always felt in a state of mild and cheerful intoxication. He felt as though he were the center of some im- portant and general movement; that something was constantly expected of him, that if he did not do it he would grieve and disappoint many people, but if he did this and that, all would bewell; and he did what was demanded of him, but still that happy result always remained in the ",
    "createdDate": "2015-08-12T17:18:18.431Z",
    "speakers": [
        "Amy Predovic",
        "Mollie Rogahn"
    ],
    "categories": [
        "happy",
        "confused",
        "angry",
        "internal"
    ]
}