{
    "mediaId": "d44d9941-e0c2-4c3e-a6cc-bffc85444ae2",
    "transcript": "\"two hussars wounded, and one knocked out,\" he added, unable to restrain a happy smile, and pronouncing the phrase \"knocked out\" with ringing distinctness. \nPURSUED by the French army of a hundred thousand men under the command of Bona- parte, encountering a population that was un- friendly to it, losing confidence in its allies, suf- fering from shortness of supplies, and compell- ed to act under conditions of war unlike any- thing that had been foreseen, the Russian army of thirty-five thous",
    "createdDate": "2018-06-06T19:20:07.967Z",
    "speakers": [
        "Amy Predovic"
    ],
    "categories": [
        "confused",
        "angry"
    ]
}